graphs_tmota/__init__.py
graphs_tmota/heapq.py
graphs_tmota/spf.py
graphs_tmota-0.0.1.dist-info/METADATA
graphs_tmota-0.0.1.dist-info/WHEEL
graphs_tmota-0.0.1.dist-info/RECORD
